radioSphere/__init__.py
radioSphere/blender_viewer.py
radioSphere/calibrateAttenuation.py
radioSphere/detectSpheres.py
radioSphere/optimisePositions.py
radioSphere/radioSphere.mplstyle
radioSphere/DEM/DEM.py
radioSphere/DEM/__init__.py
radioSphere/DEM/mercury.py
radioSphere/DEM/nddem.py
radioSphere/projectSphere/CupyProjector.py
radioSphere/projectSphere/NumbaProjector.py
radioSphere/projectSphere/__init__.py
radioSphere/projectSphere/projectSphere.py
radioSphere/projectSphere/projectorSpeedTest.py
radioSphere/scripts/__init__.py
radioSphere/scripts/calibrateManyParticles.py
radioSphere/scripts/calibrateSingleParticle.py
radioSphere/scripts/findParticles.py
radioSphere/scripts/generate_particles_with_shells.py
radioSphere/scripts/optimiseParticles.py
radioSphere-2.0.1.dist-info/LICENSE.md
radioSphere-2.0.1.dist-info/METADATA
radioSphere-2.0.1.dist-info/WHEEL
radioSphere-2.0.1.dist-info/entry_points.txt
radioSphere-2.0.1.dist-info/top_level.txt
radioSphere-2.0.1.dist-info/RECORD
