Metadata-Version: 2.1
Name: radioSphere
Version: 2.0.1
Summary: Software for the Practical Analysis of Materials
Author-email: Edward Andò <edward.ando@epfl.ch>, Benjy Marks <benjy.marks@sydney.edu.au>
Maintainer-email: Edward Andò <edward.ando@epfl.ch>, Benjy Marks <benjy.marks@sydney.edu.au>
License: GPLv3
Project-URL: Blog, https://medium.com/@RadioSphere
Project-URL: Repository, https://gricad-gitlab.univ-grenoble-alpes.fr/ttk/radioSphere
Keywords: reconstruction,deconvolution,spheres,image analysis,synthetic images
Classifier: Development Status :: 4 - Beta
Classifier: Environment :: Console
Classifier: Intended Audience :: Science/Research
Classifier: License :: OSI Approved :: GNU General Public License v3 (GPLv3)
Classifier: Operating System :: POSIX :: Linux
Classifier: Programming Language :: Python :: 3
Classifier: Programming Language :: Python :: 3.7
Classifier: Programming Language :: Python :: 3.8
Classifier: Programming Language :: Python :: 3.9
Classifier: Programming Language :: Python :: 3.10
Classifier: Programming Language :: Python :: 3 :: Only
Requires-Python: >=3.7
License-File: LICENSE.md
Requires-Dist: numpy
Requires-Dist: scipy
Requires-Dist: scikit-image
Requires-Dist: ipython
Requires-Dist: tifffile
Requires-Dist: matplotlib
Requires-Dist: tqdm
Requires-Dist: notebook
Requires-Dist: json5
Requires-Dist: numba
Provides-Extra: dev
Requires-Dist: pytest ; extra == 'dev'
Requires-Dist: sphinx ; extra == 'dev'
Requires-Dist: sphinx-rtd-theme ; extra == 'dev'
Requires-Dist: nbsphinx ; extra == 'dev'
Requires-Dist: numpydoc ; extra == 'dev'
Requires-Dist: black ; extra == 'dev'
Requires-Dist: build ; extra == 'dev'
Requires-Dist: twine ; extra == 'dev'
Provides-Extra: test
Requires-Dist: pytest-cov ; extra == 'test'
